{"chunk_definitions":[{"row":18,"row_count":1,"visible":true,"expansion_state":0,"options":{"engine":"r","label":"unnamed-chunk-49","dev":"png"},"document_id":"A585EEC3","chunk_id":"cxrdmwha4e9nc","chunk_label":"unnamed-chunk-3"},{"row":57,"row_count":1,"visible":true,"expansion_state":0,"options":{"engine":"r","label":"unnamed-chunk-50","dev":"png"},"document_id":"A585EEC3","chunk_id":"c5e6462zeb6a2","chunk_label":"unnamed-chunk-9"},{"row":64,"row_count":1,"visible":true,"expansion_state":0,"options":{"engine":"r","label":"unnamed-chunk-17","dev":"png"},"document_id":"A585EEC3","chunk_id":"c4wsxnxvxqkim","chunk_label":"unnamed-chunk-10"},{"row":73,"row_count":1,"visible":true,"expansion_state":0,"options":{"engine":"r","label":"unnamed-chunk-51","dev":"png"},"document_id":"A585EEC3","chunk_id":"cfwf9352y4eyt","chunk_label":"unnamed-chunk-11"},{"row":79,"row_count":1,"visible":true,"expansion_state":0,"options":{"engine":"r","label":"unnamed-chunk-23","dev":"png"},"document_id":"A585EEC3","chunk_id":"c1ikxlagpghi6","chunk_label":"unnamed-chunk-12"}],"doc_write_time":1747310508,"chunk_rendered_width":700}